navlib/__init__.py
navlib/cal/__init__.py
navlib/cal/cal_ahrs.py
navlib/cal/cal_dvl.py
navlib/cal/cal_mag.py
navlib/environment/__init__.py
navlib/environment/seawater.py
navlib/geo/__init__.py
navlib/geo/geography.py
navlib/lcmlog/__init__.py
navlib/lcmlog/_scan_for_lcmtypes.py
navlib/lcmlog/log_to_smat.py
navlib/lcmlog/parse_lcmlog.py
navlib/logging/__init__.py
navlib/logging/logging.py
navlib/math/__init__.py
navlib/math/filters.py
navlib/math/quaternion.py
navlib/math/se3.py
navlib/math/so3.py
navlib/math/vmath.py
navlib/mbsystem/__init__.py
navlib/mbsystem/parsers.py
navlib/nav/__init__.py
navlib/nav/attitude_estimation.py
navlib/nav/kalman_filter.py
navlib/nav/state_estimation.py
navlib/time/__init__.py
navlib/time/time.py
navlib-1.2.1.dist-info/LICENSE.txt
navlib-1.2.1.dist-info/METADATA
navlib-1.2.1.dist-info/WHEEL
navlib-1.2.1.dist-info/RECORD
