Metadata-Version: 2.3
Name: navlib
Version: 1.2.1
Summary: MBARI CoMPAS Lab Utilities for Navigation Data Processing
License: MIT
Author: srodriguez_mbari
Author-email: srodriguez@mbari.org
Requires-Python: >=3.8,<4.0
Classifier: Development Status :: 5 - Production/Stable
Classifier: Intended Audience :: Science/Research
Classifier: License :: OSI Approved :: MIT License
Classifier: Programming Language :: Python :: 3
Classifier: Programming Language :: Python :: 3.8
Classifier: Programming Language :: Python :: 3.9
Classifier: Programming Language :: Python :: 3.10
Classifier: Programming Language :: Python :: 3.11
Classifier: Programming Language :: Python :: 3.12
Classifier: Programming Language :: Python :: 3.13
Classifier: Topic :: Scientific/Engineering
Classifier: Topic :: Scientific/Engineering :: Mathematics
Classifier: Topic :: Scientific/Engineering :: Oceanography
Requires-Dist: autograd (>=1.7.0,<2.0.0)
Requires-Dist: gsw (>=3.6.19,<4.0.0)
Requires-Dist: gtsam (>=4.2,<5.0) ; python_version < "3.12"
Requires-Dist: imufusion (>=1.2.8,<2.0.0)
Requires-Dist: jax (>=0.4.1,<0.4.14) ; python_version == "3.8"
Requires-Dist: jax (>=0.4.14,<0.4.31) ; python_version == "3.9"
Requires-Dist: jax (>=0.4.31,<0.5.0) ; python_version >= "3.10"
Requires-Dist: jaxlib (>=0.4.1,<0.4.14) ; python_version == "3.8"
Requires-Dist: jaxlib (>=0.4.14,<0.4.31) ; python_version == "3.9"
Requires-Dist: jaxlib (>=0.4.31,<0.5.0) ; python_version >= "3.10"
Requires-Dist: lcm (>=1.5,<2.0)
Requires-Dist: numpy (>=1.22,<1.25) ; python_version == "3.8"
Requires-Dist: numpy (>=1.25,<2.0) ; python_version >= "3.9"
Requires-Dist: pymanopt (==2.1.1)
Requires-Dist: pyproj (>=3.3,<3.6) ; python_version == "3.8"
Requires-Dist: pyproj (>=3.6,<4.0) ; python_version >= "3.9"
Requires-Dist: scipy (==1.10.*) ; python_version == "3.8"
Requires-Dist: scipy (>=1.11,<1.14) ; python_version == "3.9"
Requires-Dist: scipy (>=1.14,<2.0) ; python_version >= "3.10"
